mrob-0.0.17.dist-info/LICENSE.md
mrob-0.0.17.dist-info/RECORD
mrob-0.0.17.dist-info/WHEEL
mrob-0.0.17.dist-info/top_level.txt
mrob-0.0.17.dist-info/METADATA
mrob/pybind.cpython-311-darwin.so
mrob/__init__.py
mrob/.dylibs/libFGraph.dylib
mrob/.dylibs/libSE3.dylib
mrob/.dylibs/libcommon.dylib
mrob/.dylibs/libvisual.dylib
mrob/.dylibs/libplane-surfaces.dylib
mrob/.dylibs/libPCRegistration.dylib
