Metadata-Version: 2.1
Name: mrob
Version: 0.0.17
Summary: Mobile Robotics library (mrob) is a framework for implementing robotics research and projects.
Home-page: https://github.com/prime-slam/mrob
Author: Gonzalo Ferrer
Author-email: G.Ferrer@skoltech.ru
Maintainer: Gonzalo Ferrer
Maintainer-email: G.Ferrer@skoltech.ru
License: Apache-2.0
Download-URL: https://github.com/prime-slam/mrob
Platform: any
Requires-Python: >=3.6
License-File: LICENSE.md
